astetik/__init__.py
astetik/extras/__init__.py
astetik/extras/clean_notebook.sh
astetik/extras/countries.csv
astetik/extras/countries.dbf
astetik/extras/countries.shp
astetik/extras/countries.shx
astetik/extras/table.html
astetik/plots/__init__.py
astetik/plots/animate.py
astetik/plots/bar.py
astetik/plots/bargrid.py
astetik/plots/bartwo.py
astetik/plots/box.py
astetik/plots/compare.py
astetik/plots/corr.py
astetik/plots/count.py
astetik/plots/grid.py
astetik/plots/hist.py
astetik/plots/kde.py
astetik/plots/line.py
astetik/plots/multicount.py
astetik/plots/multikde.py
astetik/plots/oned.py
astetik/plots/overlap.py
astetik/plots/pie.py
astetik/plots/regs.py
astetik/plots/roc.py
astetik/plots/scat.py
astetik/plots/strip.py
astetik/plots/swarm.py
astetik/plots/twod.py
astetik/plots/violin.py
astetik/plots/world.py
astetik/style/__init__.py
astetik/style/color_picker.py
astetik/style/formats.py
astetik/style/legend.py
astetik/style/random_colors.py
astetik/style/sizer.py
astetik/style/style.py
astetik/style/template.py
astetik/style/titles.py
astetik/tables/__init__.py
astetik/tables/table.py
astetik/tables/text.py
astetik/utils/__init__.py
astetik/utils/country_code.py
astetik/utils/datetime.py
astetik/utils/exceptions.py
astetik/utils/gui.py
astetik/utils/load_data.py
astetik/utils/outliers.py
astetik/utils/transform.py
astetik/utils/utils.py
astetik-1.16.dist-info/METADATA
astetik-1.16.dist-info/WHEEL
astetik-1.16.dist-info/licenses/LICENSE
astetik-1.16.dist-info/RECORD
