Metadata-Version: 2.3
Name: astetik
Version: 1.16
Summary: Astetik data visualization and reporting library
Project-URL: Download, https://github.com/mikkokotila/pretty
Project-URL: Homepage, http://mikkokotila.com
Author-email: Mikko Kotila <mailme@mikkokotila.com>
Maintainer-email: Mikko Kotila <mailme@mikkokotila.com>
License-Expression: MIT
License-File: LICENSE
Classifier: Intended Audience :: Science/Research
Classifier: License :: OSI Approved :: MIT License
Classifier: Operating System :: MacOS
Classifier: Operating System :: POSIX
Classifier: Operating System :: Unix
Classifier: Programming Language :: Python :: 2.7
Classifier: Programming Language :: Python :: 3.4
Classifier: Programming Language :: Python :: 3.5
Classifier: Programming Language :: Python :: 3.6
Classifier: Topic :: Multimedia :: Graphics
Classifier: Topic :: Scientific/Engineering :: Visualization
Requires-Dist: geonamescache
Requires-Dist: ipython
Requires-Dist: numpy
Requires-Dist: pandas
Requires-Dist: patsy
Requires-Dist: scikit-learn
Requires-Dist: seaborn
Requires-Dist: statsmodels
Requires-Dist: wrangle
